m3m3s
