Metadata-Version: 1.1
Name: m3m3s
Version: 0.0.3
Summary: Scripts for memes
Home-page: https://github.com/rileyannis/memescripts
Author: Jake Fenton
Author-email: jake@fenton.io
License: MIT License
Platform: UNKNOWN
Classifier: Development Status :: 2 - Pre-Alpha
Classifier: Intended Audience :: Developers
Classifier: License :: OSI Approved :: MIT License
Classifier: Operating System :: Unix
Classifier: Operating System :: POSIX
Classifier: Programming Language :: Python :: 3.6
Classifier: Topic :: Utilities
